{"@index":0,"@class":"android.widget.FrameLayout","@package":"com.android.settings","@checkable":false,"@checked":false,"@clickable":false,"@enabled":true,"@focusable":false,"@focused":false,"@scrollable":false,"@long-clickable":false,"@selected":false,"@editable":false,"@visible":true,"@bounds":"[0,0][1440,2560]","@screenBounds":"[0,0][1440,2560]","node":{"@index":0,"@class":"android.widget.LinearLayout","@package":"com.android.settings","@checkable":false,"@checked":false,"@clickable":false,"@enabled":true,"@focusable":false,"@focused":false,"@scrollable":false,"@long-clickable":false,"@selected":false,"@editable":false,"@visible":true,"@bounds":"[0,0][1440,2392]","@screenBounds":"[0,0][1440,2560]","node":{"@index":0,"@resource-id":"android:id\/content","@class":"android.widget.FrameLayout","@package":"com.android.settings","@checkable":false,"@checked":false,"@clickable":false,"@enabled":true,"@focusable":false,"@focused":false,"@scrollable":false,"@long-clickable":false,"@selected":false,"@editable":false,"@visible":true,"@bounds":"[0,84][1440,2392]","@screenBounds":"[0,0][1440,2560]","node":{"@index":0,"@resource-id":"com.android.settings:id\/content_parent","@class":"android.widget.LinearLayout","@package":"com.android.settings","@checkable":false,"@checked":false,"@clickable":false,"@enabled":true,"@focusable":false,"@focused":false,"@scrollable":false,"@long-clickable":false,"@selected":false,"@editable":false,"@visible":true,"@bounds":"[0,84][1440,2392]","@screenBounds":"[0,0][1440,2560]","node":[{"@index":0,"@resource-id":"com.android.settings:id\/action_bar","@class":"android.view.ViewGroup","@package":"com.android.settings","@checkable":false,"@checked":false,"@clickable":false,"@enabled":true,"@focusable":false,"@focused":false,"@scrollable":false,"@long-clickable":false,"@selected":false,"@editable":false,"@visible":true,"@bounds":"[0,84][1440,280]","@screenBounds":"[0,0][1440,2560]","node":[{"@index":0,"@class":"android.widget.ImageButton","@package":"com.android.settings","@content-desc":"Collapse","@checkable":false,"@checked":false,"@clickable":true,"@enabled":true,"@focusable":true,"@focused":false,"@scrollable":false,"@long-clickable":false,"@selected":false,"@editable":false,"@visible":true,"@bounds":"[0,84][196,280]","@screenBounds":"[0,0][1440,2560]"},{"@index":1,"@resource-id":"com.android.settings:id\/search_app_list_menu","@class":"android.widget.SearchView","@package":"com.android.settings","@checkable":false,"@checked":false,"@clickable":false,"@enabled":true,"@focusable":true,"@focused":false,"@scrollable":false,"@long-clickable":false,"@selected":false,"@editable":false,"@visible":true,"@bounds":"[252,98][1300,266]","@screenBounds":"[0,0][1440,2560]","node":{"@index":0,"@resource-id":"android:id\/search_bar","@class":"android.widget.LinearLayout","@package":"com.android.settings","@checkable":false,"@checked":false,"@clickable":false,"@enabled":true,"@focusable":false,"@focused":false,"@scrollable":false,"@long-clickable":false,"@selected":false,"@editable":false,"@visible":true,"@bounds":"[252,98][1300,266]","@screenBounds":"[0,0][1440,2560]","node":{"@index":0,"@resource-id":"android:id\/search_edit_frame","@class":"android.widget.LinearLayout","@package":"com.android.settings","@checkable":false,"@checked":false,"@clickable":false,"@enabled":true,"@focusable":false,"@focused":false,"@scrollable":false,"@long-clickable":false,"@selected":false,"@editable":false,"@visible":true,"@bounds":"[280,98][1272,266]","@screenBounds":"[0,0][1440,2560]","node":{"@index":0,"@resource-id":"android:id\/search_plate","@class":"android.widget.LinearLayout","@package":"com.android.settings","@checkable":false,"@checked":false,"@clickable":false,"@enabled":true,"@focusable":false,"@focused":false,"@scrollable":false,"@long-clickable":false,"@selected":false,"@editable":false,"@visible":true,"@bounds":"[280,98][1272,266]","@screenBounds":"[0,0][1440,2560]","node":{"@index":0,"@text":"Search","@resource-id":"android:id\/search_src_text","@class":"android.widget.EditText","@package":"com.android.settings","@checkable":false,"@checked":false,"@clickable":true,"@enabled":true,"@focusable":true,"@focused":true,"@scrollable":false,"@long-clickable":true,"@selected":false,"@editable":true,"@visible":true,"@bounds":"[280,119][1272,245]","@screenBounds":"[0,0][1440,2560]"}}}}},{"@index":2,"@class":"android.widget.LinearLayout","@package":"com.android.settings","@checkable":false,"@checked":false,"@clickable":false,"@enabled":true,"@focusable":false,"@focused":false,"@scrollable":false,"@long-clickable":false,"@selected":false,"@editable":false,"@visible":true,"@bounds":"[1300,84][1440,280]","@screenBounds":"[0,0][1440,2560]","node":{"@index":0,"@class":"android.widget.ImageButton","@package":"com.android.settings","@content-desc":"More options","@checkable":false,"@checked":false,"@clickable":true,"@enabled":true,"@focusable":true,"@focused":false,"@scrollable":false,"@long-clickable":true,"@selected":false,"@editable":false,"@visible":true,"@bounds":"[1300,98][1440,266]","@screenBounds":"[0,0][1440,2560]"}}]},{"@index":1,"@resource-id":"com.android.settings:id\/content_frame","@class":"android.widget.FrameLayout","@package":"com.android.settings","@checkable":false,"@checked":false,"@clickable":false,"@enabled":true,"@focusable":false,"@focused":false,"@scrollable":false,"@long-clickable":false,"@selected":false,"@editable":false,"@visible":true,"@bounds":"[0,280][1440,2392]","@screenBounds":"[0,0][1440,2560]","node":{"@index":0,"@class":"android.widget.LinearLayout","@package":"com.android.settings","@checkable":false,"@checked":false,"@clickable":false,"@enabled":true,"@focusable":false,"@focused":false,"@scrollable":false,"@long-clickable":false,"@selected":false,"@editable":false,"@visible":true,"@bounds":"[0,280][1440,2392]","@screenBounds":"[0,0][1440,2560]","node":{"@index":0,"@resource-id":"com.android.settings:id\/main_content","@class":"android.widget.FrameLayout","@package":"com.android.settings","@checkable":false,"@checked":false,"@clickable":false,"@enabled":true,"@focusable":false,"@focused":false,"@scrollable":false,"@long-clickable":false,"@selected":false,"@editable":false,"@visible":true,"@bounds":"[0,280][1440,2392]","@screenBounds":"[0,0][1440,2560]","node":{"@index":0,"@class":"android.view.ViewGroup","@package":"com.android.settings","@checkable":false,"@checked":false,"@clickable":false,"@enabled":true,"@focusable":false,"@focused":false,"@scrollable":false,"@long-clickable":false,"@selected":false,"@editable":false,"@visible":true,"@bounds":"[0,280][1440,2392]","@screenBounds":"[0,0][1440,2560]","node":{"@index":0,"@class":"android.widget.FrameLayout","@package":"com.android.settings","@checkable":false,"@checked":false,"@clickable":false,"@enabled":true,"@focusable":false,"@focused":false,"@scrollable":false,"@long-clickable":false,"@selected":false,"@editable":false,"@visible":true,"@bounds":"[0,280][1440,2392]","@screenBounds":"[0,0][1440,2560]","node":{"@index":0,"@resource-id":"com.android.settings:id\/list_container","@class":"android.widget.FrameLayout","@package":"com.android.settings","@checkable":false,"@checked":false,"@clickable":false,"@enabled":true,"@focusable":false,"@focused":false,"@scrollable":false,"@long-clickable":false,"@selected":false,"@editable":false,"@visible":true,"@bounds":"[0,280][1440,2392]","@screenBounds":"[0,0][1440,2560]","node":{"@index":0,"@resource-id":"com.android.settings:id\/apps_list","@class":"androidx.recyclerview.widget.RecyclerView","@package":"com.android.settings","@checkable":false,"@checked":false,"@clickable":false,"@enabled":true,"@focusable":true,"@focused":false,"@scrollable":true,"@long-clickable":false,"@selected":false,"@editable":false,"@visible":true,"@bounds":"[0,280][1440,2392]","@screenBounds":"[0,0][1440,2560]","node":[{"@index":0,"@class":"android.widget.LinearLayout","@package":"com.android.settings","@content-desc":"ActionRecord","@checkable":false,"@checked":false,"@clickable":true,"@enabled":true,"@focusable":true,"@focused":false,"@scrollable":false,"@long-clickable":false,"@selected":false,"@editable":false,"@visible":true,"@bounds":"[0,280][1440,534]","@screenBounds":"[0,0][1440,2560]","node":{"@index":0,"@class":"android.widget.LinearLayout","@package":"com.android.settings","@checkable":false,"@checked":false,"@clickable":false,"@enabled":true,"@focusable":false,"@focused":false,"@scrollable":false,"@long-clickable":false,"@selected":false,"@editable":false,"@visible":true,"@bounds":"[252,280][1384,534]","@screenBounds":"[0,0][1440,2560]","node":[{"@index":0,"@text":"ActionRecord","@resource-id":"android:id\/title","@class":"android.widget.TextView","@package":"com.android.settings","@checkable":false,"@checked":false,"@clickable":false,"@enabled":true,"@focusable":false,"@focused":false,"@scrollable":false,"@long-clickable":false,"@selected":false,"@editable":false,"@visible":true,"@bounds":"[252,336][590,412]","@screenBounds":"[0,0][1440,2560]"},{"@index":1,"@text":"36.05 MB","@resource-id":"android:id\/summary","@class":"android.widget.TextView","@package":"com.android.settings","@checkable":false,"@checked":false,"@clickable":false,"@enabled":true,"@focusable":false,"@focused":false,"@scrollable":false,"@long-clickable":false,"@selected":false,"@editable":false,"@visible":true,"@bounds":"[252,412][1384,478]","@screenBounds":"[0,0][1440,2560]"}]}},{"@index":1,"@class":"android.widget.LinearLayout","@package":"com.android.settings","@content-desc":"Android Auto","@checkable":false,"@checked":false,"@clickable":true,"@enabled":true,"@focusable":true,"@focused":false,"@scrollable":false,"@long-clickable":false,"@selected":false,"@editable":false,"@visible":true,"@bounds":"[0,534][1440,788]","@screenBounds":"[0,0][1440,2560]","node":{"@index":0,"@class":"android.widget.LinearLayout","@package":"com.android.settings","@checkable":false,"@checked":false,"@clickable":false,"@enabled":true,"@focusable":false,"@focused":false,"@scrollable":false,"@long-clickable":false,"@selected":false,"@editable":false,"@visible":true,"@bounds":"[252,534][1384,788]","@screenBounds":"[0,0][1440,2560]","node":[{"@index":0,"@text":"Android Auto","@resource-id":"android:id\/title","@class":"android.widget.TextView","@package":"com.android.settings","@checkable":false,"@checked":false,"@clickable":false,"@enabled":true,"@focusable":false,"@focused":false,"@scrollable":false,"@long-clickable":false,"@selected":false,"@editable":false,"@visible":true,"@bounds":"[252,590][580,666]","@screenBounds":"[0,0][1440,2560]"},{"@index":1,"@text":"168 kB","@resource-id":"android:id\/summary","@class":"android.widget.TextView","@package":"com.android.settings","@checkable":false,"@checked":false,"@clickable":false,"@enabled":true,"@focusable":false,"@focused":false,"@scrollable":false,"@long-clickable":false,"@selected":false,"@editable":false,"@visible":true,"@bounds":"[252,666][1384,732]","@screenBounds":"[0,0][1440,2560]"}]}},{"@index":2,"@class":"android.widget.LinearLayout","@package":"com.android.settings","@content-desc":"Calendar","@checkable":false,"@checked":false,"@clickable":true,"@enabled":true,"@focusable":true,"@focused":false,"@scrollable":false,"@long-clickable":false,"@selected":false,"@editable":false,"@visible":true,"@bounds":"[0,788][1440,1042]","@screenBounds":"[0,0][1440,2560]","node":{"@index":0,"@class":"android.widget.LinearLayout","@package":"com.android.settings","@checkable":false,"@checked":false,"@clickable":false,"@enabled":true,"@focusable":false,"@focused":false,"@scrollable":false,"@long-clickable":false,"@selected":false,"@editable":false,"@visible":true,"@bounds":"[252,788][1384,1042]","@screenBounds":"[0,0][1440,2560]","node":[{"@index":0,"@text":"Calendar","@resource-id":"android:id\/title","@class":"android.widget.TextView","@package":"com.android.settings","@checkable":false,"@checked":false,"@clickable":false,"@enabled":true,"@focusable":false,"@focused":false,"@scrollable":false,"@long-clickable":false,"@selected":false,"@editable":false,"@visible":true,"@bounds":"[252,844][474,920]","@screenBounds":"[0,0][1440,2560]"},{"@index":1,"@text":"717 kB","@resource-id":"android:id\/summary","@class":"android.widget.TextView","@package":"com.android.settings","@checkable":false,"@checked":false,"@clickable":false,"@enabled":true,"@focusable":false,"@focused":false,"@scrollable":false,"@long-clickable":false,"@selected":false,"@editable":false,"@visible":true,"@bounds":"[252,920][1384,986]","@screenBounds":"[0,0][1440,2560]"}]}},{"@index":3,"@class":"android.widget.LinearLayout","@package":"com.android.settings","@content-desc":"Camera","@checkable":false,"@checked":false,"@clickable":true,"@enabled":true,"@focusable":true,"@focused":false,"@scrollable":false,"@long-clickable":false,"@selected":false,"@editable":false,"@visible":true,"@bounds":"[0,1042][1440,1296]","@screenBounds":"[0,0][1440,2560]","node":{"@index":0,"@class":"android.widget.LinearLayout","@package":"com.android.settings","@checkable":false,"@checked":false,"@clickable":false,"@enabled":true,"@focusable":false,"@focused":false,"@scrollable":false,"@long-clickable":false,"@selected":false,"@editable":false,"@visible":true,"@bounds":"[252,1042][1384,1296]","@screenBounds":"[0,0][1440,2560]","node":[{"@index":0,"@text":"Camera","@resource-id":"android:id\/title","@class":"android.widget.TextView","@package":"com.android.settings","@checkable":false,"@checked":false,"@clickable":false,"@enabled":true,"@focusable":false,"@focused":false,"@scrollable":false,"@long-clickable":false,"@selected":false,"@editable":false,"@visible":true,"@bounds":"[252,1098][445,1174]","@screenBounds":"[0,0][1440,2560]"},{"@index":1,"@text":"40.96 kB","@resource-id":"android:id\/summary","@class":"android.widget.TextView","@package":"com.android.settings","@checkable":false,"@checked":false,"@clickable":false,"@enabled":true,"@focusable":false,"@focused":false,"@scrollable":false,"@long-clickable":false,"@selected":false,"@editable":false,"@visible":true,"@bounds":"[252,1174][1384,1240]","@screenBounds":"[0,0][1440,2560]"}]}},{"@index":4,"@class":"android.widget.LinearLayout","@package":"com.android.settings","@content-desc":"Chrome","@checkable":false,"@checked":false,"@clickable":true,"@enabled":true,"@focusable":true,"@focused":false,"@scrollable":false,"@long-clickable":false,"@selected":false,"@editable":false,"@visible":true,"@bounds":"[0,1296][1440,1550]","@screenBounds":"[0,0][1440,2560]","node":{"@index":0,"@class":"android.widget.LinearLayout","@package":"com.android.settings","@checkable":false,"@checked":false,"@clickable":false,"@enabled":true,"@focusable":false,"@focused":false,"@scrollable":false,"@long-clickable":false,"@selected":false,"@editable":false,"@visible":true,"@bounds":"[252,1296][1384,1550]","@screenBounds":"[0,0][1440,2560]","node":[{"@index":0,"@text":"Chrome","@resource-id":"android:id\/title","@class":"android.widget.TextView","@package":"com.android.settings","@checkable":false,"@checked":false,"@clickable":false,"@enabled":true,"@focusable":false,"@focused":false,"@scrollable":false,"@long-clickable":false,"@selected":false,"@editable":false,"@visible":true,"@bounds":"[252,1352][449,1428]","@screenBounds":"[0,0][1440,2560]"},{"@index":1,"@text":"10.38 MB","@resource-id":"android:id\/summary","@class":"android.widget.TextView","@package":"com.android.settings","@checkable":false,"@checked":false,"@clickable":false,"@enabled":true,"@focusable":false,"@focused":false,"@scrollable":false,"@long-clickable":false,"@selected":false,"@editable":false,"@visible":true,"@bounds":"[252,1428][1384,1494]","@screenBounds":"[0,0][1440,2560]"}]}},{"@index":5,"@class":"android.widget.LinearLayout","@package":"com.android.settings","@content-desc":"Clock","@checkable":false,"@checked":false,"@clickable":true,"@enabled":true,"@focusable":true,"@focused":false,"@scrollable":false,"@long-clickable":false,"@selected":false,"@editable":false,"@visible":true,"@bounds":"[0,1550][1440,1804]","@screenBounds":"[0,0][1440,2560]","node":{"@index":0,"@class":"android.widget.LinearLayout","@package":"com.android.settings","@checkable":false,"@checked":false,"@clickable":false,"@enabled":true,"@focusable":false,"@focused":false,"@scrollable":false,"@long-clickable":false,"@selected":false,"@editable":false,"@visible":true,"@bounds":"[252,1550][1384,1804]","@screenBounds":"[0,0][1440,2560]","node":[{"@index":0,"@text":"Clock","@resource-id":"android:id\/title","@class":"android.widget.TextView","@package":"com.android.settings","@checkable":false,"@checked":false,"@clickable":false,"@enabled":true,"@focusable":false,"@focused":false,"@scrollable":false,"@long-clickable":false,"@selected":false,"@editable":false,"@visible":true,"@bounds":"[252,1606][391,1682]","@screenBounds":"[0,0][1440,2560]"},{"@index":1,"@text":"172 kB","@resource-id":"android:id\/summary","@class":"android.widget.TextView","@package":"com.android.settings","@checkable":false,"@checked":false,"@clickable":false,"@enabled":true,"@focusable":false,"@focused":false,"@scrollable":false,"@long-clickable":false,"@selected":false,"@editable":false,"@visible":true,"@bounds":"[252,1682][1384,1748]","@screenBounds":"[0,0][1440,2560]"}]}},{"@index":6,"@class":"android.widget.LinearLayout","@package":"com.android.settings","@content-desc":"Contacts","@checkable":false,"@checked":false,"@clickable":true,"@enabled":true,"@focusable":true,"@focused":false,"@scrollable":false,"@long-clickable":false,"@selected":false,"@editable":false,"@visible":true,"@bounds":"[0,1804][1440,2058]","@screenBounds":"[0,0][1440,2560]","node":{"@index":0,"@class":"android.widget.LinearLayout","@package":"com.android.settings","@checkable":false,"@checked":false,"@clickable":false,"@enabled":true,"@focusable":false,"@focused":false,"@scrollable":false,"@long-clickable":false,"@selected":false,"@editable":false,"@visible":true,"@bounds":"[252,1804][1384,2058]","@screenBounds":"[0,0][1440,2560]","node":[{"@index":0,"@text":"Contacts","@resource-id":"android:id\/title","@class":"android.widget.TextView","@package":"com.android.settings","@checkable":false,"@checked":false,"@clickable":false,"@enabled":true,"@focusable":false,"@focused":false,"@scrollable":false,"@long-clickable":false,"@selected":false,"@editable":false,"@visible":true,"@bounds":"[252,1860][475,1936]","@screenBounds":"[0,0][1440,2560]"},{"@index":1,"@text":"32.77 kB","@resource-id":"android:id\/summary","@class":"android.widget.TextView","@package":"com.android.settings","@checkable":false,"@checked":false,"@clickable":false,"@enabled":true,"@focusable":false,"@focused":false,"@scrollable":false,"@long-clickable":false,"@selected":false,"@editable":false,"@visible":true,"@bounds":"[252,1936][1384,2002]","@screenBounds":"[0,0][1440,2560]"}]}},{"@index":7,"@class":"android.widget.LinearLayout","@package":"com.android.settings","@content-desc":"Digital Wellbeing","@checkable":false,"@checked":false,"@clickable":true,"@enabled":true,"@focusable":true,"@focused":false,"@scrollable":false,"@long-clickable":false,"@selected":false,"@editable":false,"@visible":true,"@bounds":"[0,2058][1440,2312]","@screenBounds":"[0,0][1440,2560]","node":{"@index":0,"@class":"android.widget.LinearLayout","@package":"com.android.settings","@checkable":false,"@checked":false,"@clickable":false,"@enabled":true,"@focusable":false,"@focused":false,"@scrollable":false,"@long-clickable":false,"@selected":false,"@editable":false,"@visible":true,"@bounds":"[252,2058][1384,2312]","@screenBounds":"[0,0][1440,2560]","node":[{"@index":0,"@text":"Digital Wellbeing","@resource-id":"android:id\/title","@class":"android.widget.TextView","@package":"com.android.settings","@checkable":false,"@checked":false,"@clickable":false,"@enabled":true,"@focusable":false,"@focused":false,"@scrollable":false,"@long-clickable":false,"@selected":false,"@editable":false,"@visible":true,"@bounds":"[252,2114][669,2190]","@screenBounds":"[0,0][1440,2560]"},{"@index":1,"@text":"1.99 MB","@resource-id":"android:id\/summary","@class":"android.widget.TextView","@package":"com.android.settings","@checkable":false,"@checked":false,"@clickable":false,"@enabled":true,"@focusable":false,"@focused":false,"@scrollable":false,"@long-clickable":false,"@selected":false,"@editable":false,"@visible":true,"@bounds":"[252,2190][1384,2256]","@screenBounds":"[0,0][1440,2560]"}]}},{"@index":8,"@class":"android.widget.LinearLayout","@package":"com.android.settings","@content-desc":"Drive","@checkable":false,"@checked":false,"@clickable":true,"@enabled":true,"@focusable":true,"@focused":false,"@scrollable":false,"@long-clickable":false,"@selected":false,"@editable":false,"@visible":true,"@bounds":"[0,2312][1440,2392]","@screenBounds":"[0,0][1440,2560]","node":{"@index":0,"@class":"android.widget.LinearLayout","@package":"com.android.settings","@checkable":false,"@checked":false,"@clickable":false,"@enabled":true,"@focusable":false,"@focused":false,"@scrollable":false,"@long-clickable":false,"@selected":false,"@editable":false,"@visible":true,"@bounds":"[252,2312][1384,2392]","@screenBounds":"[0,0][1440,2560]","node":{"@index":0,"@text":"Drive","@resource-id":"android:id\/title","@class":"android.widget.TextView","@package":"com.android.settings","@checkable":false,"@checked":false,"@clickable":false,"@enabled":true,"@focusable":false,"@focused":false,"@scrollable":false,"@long-clickable":false,"@selected":false,"@editable":false,"@visible":true,"@bounds":"[252,2368][379,2392]","@screenBounds":"[0,0][1440,2560]"}}}]}}}}}}}]}}}}