{"@index":0,"@class":"android.widget.FrameLayout","@package":"com.google.android.gm","@checkable":false,"@checked":false,"@clickable":false,"@enabled":true,"@focusable":false,"@focused":false,"@scrollable":false,"@long-clickable":false,"@selected":false,"@editable":false,"@bounds":"[0,0][1080,2280]","@screenBounds":"[0,0][1080,2280]","node":{"@index":0,"@class":"android.widget.LinearLayout","@package":"com.google.android.gm","@checkable":false,"@checked":false,"@clickable":false,"@enabled":true,"@focusable":false,"@focused":false,"@scrollable":false,"@long-clickable":false,"@selected":false,"@editable":false,"@bounds":"[0,0][1080,2214]","@screenBounds":"[0,0][1080,2280]","node":{"@index":0,"@class":"android.widget.FrameLayout","@package":"com.google.android.gm","@checkable":false,"@checked":false,"@clickable":false,"@enabled":true,"@focusable":false,"@focused":false,"@scrollable":false,"@long-clickable":false,"@selected":false,"@editable":false,"@bounds":"[0,66][1080,2214]","@screenBounds":"[0,0][1080,2280]","node":{"@index":0,"@resource-id":"com.google.android.gm:id\/action_bar_root","@class":"android.widget.FrameLayout","@package":"com.google.android.gm","@checkable":false,"@checked":false,"@clickable":false,"@enabled":true,"@focusable":false,"@focused":false,"@scrollable":false,"@long-clickable":false,"@selected":false,"@editable":false,"@bounds":"[0,66][1080,2214]","@screenBounds":"[0,0][1080,2280]","node":{"@index":0,"@resource-id":"android:id\/content","@class":"android.widget.FrameLayout","@package":"com.google.android.gm","@checkable":false,"@checked":false,"@clickable":false,"@enabled":true,"@focusable":false,"@focused":false,"@scrollable":false,"@long-clickable":false,"@selected":false,"@editable":false,"@bounds":"[0,66][1080,2214]","@screenBounds":"[0,0][1080,2280]","node":{"@index":0,"@resource-id":"com.google.android.gm:id\/drawer_container","@class":"androidx.drawerlayout.widget.DrawerLayout","@package":"com.google.android.gm","@checkable":false,"@checked":false,"@clickable":false,"@enabled":true,"@focusable":false,"@focused":false,"@scrollable":false,"@long-clickable":false,"@selected":false,"@editable":false,"@bounds":"[0,66][1080,2214]","@screenBounds":"[0,0][1080,2280]","node":[{"@index":0,"@resource-id":"com.google.android.gm:id\/content_pane","@class":"android.widget.RelativeLayout","@package":"com.google.android.gm","@checkable":false,"@checked":false,"@clickable":false,"@enabled":true,"@focusable":false,"@focused":false,"@scrollable":false,"@long-clickable":false,"@selected":false,"@editable":false,"@bounds":"[0,66][1080,2214]","@screenBounds":"[0,0][1080,2280]","node":[{"@index":0,"@resource-id":"com.google.android.gm:id\/content_without_bottom_nav_bar","@class":"android.widget.RelativeLayout","@package":"com.google.android.gm","@checkable":false,"@checked":false,"@clickable":false,"@enabled":true,"@focusable":false,"@focused":false,"@scrollable":false,"@long-clickable":false,"@selected":false,"@editable":false,"@bounds":"[0,66][1080,2082]","@screenBounds":"[0,0][1080,2280]","node":{"@index":0,"@class":"android.widget.FrameLayout","@package":"com.google.android.gm","@checkable":false,"@checked":false,"@clickable":false,"@enabled":true,"@focusable":false,"@focused":false,"@scrollable":false,"@long-clickable":false,"@selected":false,"@editable":false,"@bounds":"[0,66][1080,2082]","@screenBounds":"[0,0][1080,2280]","node":[{"@index":0,"@resource-id":"com.google.android.gm:id\/conversation_list_place_holder","@class":"android.widget.FrameLayout","@package":"com.google.android.gm","@checkable":false,"@checked":false,"@clickable":false,"@enabled":true,"@focusable":false,"@focused":false,"@scrollable":false,"@long-clickable":false,"@selected":false,"@editable":false,"@bounds":"[0,66][1080,2082]","@screenBounds":"[0,0][1080,2280]","node":{"@index":0,"@class":"android.widget.ScrollView","@package":"com.google.android.gm","@checkable":false,"@checked":false,"@clickable":false,"@enabled":true,"@focusable":false,"@focused":false,"@scrollable":true,"@long-clickable":false,"@selected":false,"@editable":false,"@bounds":"[0,66][1080,2082]","@screenBounds":"[0,0][1080,2280]","node":[{"@index":0,"@resource-id":"com.google.android.gm:id\/osb_app_bar_layout","@class":"android.widget.LinearLayout","@package":"com.google.android.gm","@checkable":false,"@checked":false,"@clickable":false,"@enabled":true,"@focusable":false,"@focused":false,"@scrollable":false,"@long-clickable":false,"@selected":false,"@editable":false,"@bounds":"[0,66][1080,242]","@screenBounds":"[0,0][1080,2280]","node":{"@index":0,"@text":"Search in mail","@resource-id":"com.google.android.gm:id\/open_search","@class":"android.widget.EditText","@package":"com.google.android.gm","@checkable":false,"@checked":false,"@clickable":true,"@enabled":true,"@focusable":true,"@focused":false,"@scrollable":false,"@long-clickable":false,"@selected":false,"@editable":false,"@bounds":"[44,88][1036,220]","@screenBounds":"[0,0][1080,2280]","node":[{"@index":0,"@class":"android.widget.ImageButton","@package":"com.google.android.gm","@content-desc":"Open navigation drawer","@checkable":false,"@checked":false,"@clickable":true,"@enabled":true,"@focusable":true,"@focused":false,"@scrollable":false,"@long-clickable":false,"@selected":false,"@editable":false,"@bounds":"[55,88][187,220]","@screenBounds":"[0,0][1080,2280]"},{"@index":1,"@text":"Search in mail","@resource-id":"com.google.android.gm:id\/open_search_bar_text_view","@class":"android.widget.TextView","@package":"com.google.android.gm","@checkable":false,"@checked":false,"@clickable":false,"@enabled":true,"@focusable":false,"@focused":false,"@scrollable":false,"@long-clickable":false,"@selected":false,"@editable":false,"@bounds":"[187,122][461,186]","@screenBounds":"[0,0][1080,2280]"},{"@index":2,"@class":"android.support.v7.widget.LinearLayoutCompat","@package":"com.google.android.gm","@checkable":false,"@checked":false,"@clickable":false,"@enabled":true,"@focusable":false,"@focused":false,"@scrollable":false,"@long-clickable":false,"@selected":false,"@editable":false,"@bounds":"[896,88][1036,220]","@screenBounds":"[0,0][1080,2280]","node":{"@index":0,"@resource-id":"com.google.android.gm:id\/selected_account_disc_gmail","@class":"android.widget.FrameLayout","@package":"com.google.android.gm","@content-desc":"Signed in as Bowen Wang saltyp0rridge20@gmail.com\nAccount and settings.","@checkable":false,"@checked":false,"@clickable":true,"@enabled":true,"@focusable":true,"@focused":false,"@scrollable":false,"@long-clickable":false,"@selected":false,"@editable":false,"@bounds":"[896,88][1036,220]","@screenBounds":"[0,0][1080,2280]"}}]}},{"@index":1,"@resource-id":"com.google.android.gm:id\/swipe_refresh_widget","@class":"android.view.ViewGroup","@package":"com.google.android.gm","@checkable":false,"@checked":false,"@clickable":false,"@enabled":true,"@focusable":false,"@focused":false,"@scrollable":false,"@long-clickable":false,"@selected":false,"@editable":false,"@bounds":"[0,66][1080,2082]","@screenBounds":"[0,0][1080,2280]","node":{"@index":0,"@resource-id":"com.google.android.gm:id\/conversation_list_parent_frame","@class":"android.widget.FrameLayout","@package":"com.google.android.gm","@checkable":false,"@checked":false,"@clickable":false,"@enabled":true,"@focusable":false,"@focused":false,"@scrollable":false,"@long-clickable":false,"@selected":false,"@editable":false,"@bounds":"[0,66][1080,2082]","@screenBounds":"[0,0][1080,2280]","node":{"@index":0,"@resource-id":"com.google.android.gm:id\/empty_view","@class":"android.widget.RelativeLayout","@package":"com.google.android.gm","@checkable":false,"@checked":false,"@clickable":false,"@enabled":true,"@focusable":false,"@focused":false,"@scrollable":false,"@long-clickable":false,"@selected":false,"@editable":false,"@bounds":"[0,66][1080,2082]","@screenBounds":"[0,0][1080,2280]","node":{"@index":0,"@class":"android.widget.LinearLayout","@package":"com.google.android.gm","@checkable":false,"@checked":false,"@clickable":false,"@enabled":true,"@focusable":false,"@focused":false,"@scrollable":false,"@long-clickable":false,"@selected":false,"@editable":false,"@bounds":"[0,723][1080,1601]","@screenBounds":"[0,0][1080,2280]","node":{"@index":0,"@text":"Nothing in Outbox","@resource-id":"com.google.android.gm:id\/empty_text","@class":"android.widget.TextView","@package":"com.google.android.gm","@checkable":false,"@checked":false,"@clickable":false,"@enabled":true,"@focusable":false,"@focused":false,"@scrollable":false,"@long-clickable":false,"@selected":false,"@editable":false,"@bounds":"[226,1273][853,1353]","@screenBounds":"[0,0][1080,2280]"}}}}}]}},{"@index":1,"@resource-id":"com.google.android.gm:id\/toast_bar","@class":"android.widget.LinearLayout","@package":"com.google.android.gm","@content-desc":"Dismissed","@checkable":false,"@checked":false,"@clickable":false,"@enabled":true,"@focusable":false,"@focused":false,"@scrollable":false,"@long-clickable":false,"@selected":false,"@editable":false,"@bounds":"[0,1878][1080,2082]","@screenBounds":"[0,0][1080,2280]","node":{"@index":0,"@text":"Compose","@resource-id":"com.google.android.gm:id\/compose_button","@class":"android.widget.Button","@package":"com.google.android.gm","@content-desc":"Compose","@checkable":false,"@checked":false,"@clickable":true,"@enabled":true,"@focusable":true,"@focused":false,"@scrollable":false,"@long-clickable":false,"@selected":false,"@editable":false,"@bounds":"[643,1884][1014,2038]","@screenBounds":"[0,0][1080,2280]"}}]}},{"@index":1,"@resource-id":"com.google.android.gm:id\/hub_tabs_nav","@class":"android.widget.FrameLayout","@package":"com.google.android.gm","@checkable":false,"@checked":false,"@clickable":false,"@enabled":true,"@focusable":false,"@focused":false,"@scrollable":false,"@long-clickable":false,"@selected":false,"@editable":false,"@bounds":"[0,2082][1080,2214]","@screenBounds":"[0,0][1080,2280]","node":{"@index":0,"@class":"android.view.ViewGroup","@package":"com.google.android.gm","@checkable":false,"@checked":false,"@clickable":false,"@enabled":true,"@focusable":false,"@focused":false,"@scrollable":false,"@long-clickable":false,"@selected":false,"@editable":false,"@bounds":"[77,2082][1003,2214]","@screenBounds":"[0,0][1080,2280]","node":[{"@index":0,"@class":"android.widget.FrameLayout","@package":"com.google.android.gm","@content-desc":"Mail, 1 new notification","@checkable":false,"@checked":false,"@clickable":false,"@enabled":true,"@focusable":true,"@focused":false,"@scrollable":false,"@long-clickable":false,"@selected":true,"@editable":false,"@bounds":"[77,2082][540,2214]","@screenBounds":"[0,0][1080,2280]"},{"@index":1,"@class":"android.widget.FrameLayout","@package":"com.google.android.gm","@content-desc":"Meet","@checkable":false,"@checked":false,"@clickable":true,"@enabled":true,"@focusable":true,"@focused":false,"@scrollable":false,"@long-clickable":false,"@selected":false,"@editable":false,"@bounds":"[540,2082][1003,2214]","@screenBounds":"[0,0][1080,2280]"}]}}]},{"@index":1,"@resource-id":"com.google.android.gm:id\/drawer_content","@class":"android.widget.FrameLayout","@package":"com.google.android.gm","@checkable":false,"@checked":false,"@clickable":false,"@enabled":true,"@focusable":false,"@focused":false,"@scrollable":false,"@long-clickable":false,"@selected":false,"@editable":false,"@bounds":"[0,66][836,2214]","@screenBounds":"[0,0][1080,2280]","node":{"@index":0,"@resource-id":"com.google.android.gm:id\/hub_drawer_content","@class":"android.widget.FrameLayout","@package":"com.google.android.gm","@checkable":false,"@checked":false,"@clickable":false,"@enabled":true,"@focusable":false,"@focused":false,"@scrollable":false,"@long-clickable":false,"@selected":false,"@editable":false,"@bounds":"[0,66][836,2214]","@screenBounds":"[0,0][1080,2280]","node":{"@index":0,"@resource-id":"android:id\/list","@class":"android.support.v7.widget.RecyclerView","@package":"com.google.android.gm","@checkable":false,"@checked":false,"@clickable":false,"@enabled":true,"@focusable":true,"@focused":false,"@scrollable":true,"@long-clickable":false,"@selected":false,"@editable":false,"@bounds":"[0,66][836,2214]","@screenBounds":"[0,0][1080,2280]","node":[{"@index":0,"@class":"android.widget.LinearLayout","@package":"com.google.android.gm","@checkable":false,"@checked":false,"@clickable":false,"@enabled":true,"@focusable":false,"@focused":false,"@scrollable":false,"@long-clickable":false,"@selected":false,"@editable":false,"@bounds":"[0,66][836,190]","@screenBounds":"[0,0][1080,2280]","node":{"@index":0,"@resource-id":"com.google.android.gm:id\/hub_drawer_app_header","@class":"android.view.ViewGroup","@package":"com.google.android.gm","@content-desc":"Gmail","@checkable":false,"@checked":false,"@clickable":false,"@enabled":true,"@focusable":false,"@focused":false,"@scrollable":false,"@long-clickable":false,"@selected":false,"@editable":false,"@bounds":"[66,82][208,149]","@screenBounds":"[0,0][1080,2280]","node":{"@index":0,"@text":"Gmail","@resource-id":"com.google.android.gm:id\/product_name","@class":"android.widget.TextView","@package":"com.google.android.gm","@checkable":false,"@checked":false,"@clickable":false,"@enabled":true,"@focusable":false,"@focused":false,"@scrollable":false,"@long-clickable":false,"@selected":false,"@editable":false,"@bounds":"[66,82][208,149]","@screenBounds":"[0,0][1080,2280]"}}},{"@index":1,"@resource-id":"com.google.android.gm:id\/label_view","@class":"android.widget.LinearLayout","@package":"com.google.android.gm","@checkable":false,"@checked":false,"@clickable":false,"@enabled":true,"@focusable":false,"@focused":false,"@scrollable":false,"@long-clickable":false,"@selected":false,"@editable":false,"@bounds":"[0,235][836,367]","@screenBounds":"[0,0][1080,2280]","node":{"@index":0,"@resource-id":"com.google.android.gm:id\/hub_drawer_label_container","@class":"android.widget.LinearLayout","@package":"com.google.android.gm","@checkable":false,"@checked":false,"@clickable":true,"@enabled":true,"@focusable":true,"@focused":false,"@scrollable":false,"@long-clickable":false,"@selected":false,"@editable":false,"@bounds":"[0,235][836,367]","@screenBounds":"[0,0][1080,2280]","node":[{"@index":0,"@text":"Primary","@resource-id":"com.google.android.gm:id\/hub_drawer_label_title","@class":"android.widget.TextView","@package":"com.google.android.gm","@checkable":false,"@checked":false,"@clickable":false,"@enabled":true,"@focusable":false,"@focused":false,"@scrollable":false,"@long-clickable":false,"@selected":false,"@editable":false,"@bounds":"[198,270][594,331]","@screenBounds":"[0,0][1080,2280]"},{"@index":1,"@text":"1","@resource-id":"com.google.android.gm:id\/count","@class":"android.widget.TextView","@package":"com.google.android.gm","@checkable":false,"@checked":false,"@clickable":false,"@enabled":true,"@focusable":false,"@focused":false,"@scrollable":false,"@long-clickable":false,"@selected":false,"@editable":false,"@bounds":"[660,275][770,327]","@screenBounds":"[0,0][1080,2280]"}]}},{"@index":2,"@resource-id":"com.google.android.gm:id\/label_view","@class":"android.widget.LinearLayout","@package":"com.google.android.gm","@checkable":false,"@checked":false,"@clickable":false,"@enabled":true,"@focusable":false,"@focused":false,"@scrollable":false,"@long-clickable":false,"@selected":false,"@editable":false,"@bounds":"[0,367][836,499]","@screenBounds":"[0,0][1080,2280]","node":{"@index":0,"@resource-id":"com.google.android.gm:id\/hub_drawer_label_container","@class":"android.widget.LinearLayout","@package":"com.google.android.gm","@checkable":false,"@checked":false,"@clickable":true,"@enabled":true,"@focusable":true,"@focused":false,"@scrollable":false,"@long-clickable":false,"@selected":false,"@editable":false,"@bounds":"[0,367][836,499]","@screenBounds":"[0,0][1080,2280]","node":{"@index":0,"@text":"Promotions","@resource-id":"com.google.android.gm:id\/hub_drawer_label_title","@class":"android.widget.TextView","@package":"com.google.android.gm","@checkable":false,"@checked":false,"@clickable":false,"@enabled":true,"@focusable":false,"@focused":false,"@scrollable":false,"@long-clickable":false,"@selected":false,"@editable":false,"@bounds":"[198,402][814,463]","@screenBounds":"[0,0][1080,2280]"}}},{"@index":3,"@resource-id":"com.google.android.gm:id\/label_view","@class":"android.widget.LinearLayout","@package":"com.google.android.gm","@checkable":false,"@checked":false,"@clickable":false,"@enabled":true,"@focusable":false,"@focused":false,"@scrollable":false,"@long-clickable":false,"@selected":false,"@editable":false,"@bounds":"[0,499][836,631]","@screenBounds":"[0,0][1080,2280]","node":{"@index":0,"@resource-id":"com.google.android.gm:id\/hub_drawer_label_container","@class":"android.widget.LinearLayout","@package":"com.google.android.gm","@checkable":false,"@checked":false,"@clickable":true,"@enabled":true,"@focusable":true,"@focused":false,"@scrollable":false,"@long-clickable":false,"@selected":false,"@editable":false,"@bounds":"[0,499][836,631]","@screenBounds":"[0,0][1080,2280]","node":{"@index":0,"@text":"Social","@resource-id":"com.google.android.gm:id\/hub_drawer_label_title","@class":"android.widget.TextView","@package":"com.google.android.gm","@checkable":false,"@checked":false,"@clickable":false,"@enabled":true,"@focusable":false,"@focused":false,"@scrollable":false,"@long-clickable":false,"@selected":false,"@editable":false,"@bounds":"[198,534][814,595]","@screenBounds":"[0,0][1080,2280]"}}},{"@index":4,"@class":"android.widget.LinearLayout","@package":"com.google.android.gm","@checkable":false,"@checked":false,"@clickable":false,"@enabled":true,"@focusable":false,"@focused":false,"@scrollable":false,"@long-clickable":false,"@selected":false,"@editable":false,"@bounds":"[0,631][836,749]","@screenBounds":"[0,0][1080,2280]","node":{"@index":0,"@text":"All labels","@resource-id":"com.google.android.gm:id\/drawer_category_title","@class":"android.widget.TextView","@package":"com.google.android.gm","@checkable":false,"@checked":false,"@clickable":false,"@enabled":true,"@focusable":false,"@focused":false,"@scrollable":false,"@long-clickable":false,"@selected":false,"@editable":false,"@bounds":"[0,631][836,749]","@screenBounds":"[0,0][1080,2280]"}},{"@index":5,"@resource-id":"com.google.android.gm:id\/label_view","@class":"android.widget.LinearLayout","@package":"com.google.android.gm","@checkable":false,"@checked":false,"@clickable":false,"@enabled":true,"@focusable":false,"@focused":false,"@scrollable":false,"@long-clickable":false,"@selected":false,"@editable":false,"@bounds":"[0,749][836,881]","@screenBounds":"[0,0][1080,2280]","node":{"@index":0,"@resource-id":"com.google.android.gm:id\/hub_drawer_label_container","@class":"android.widget.LinearLayout","@package":"com.google.android.gm","@checkable":false,"@checked":false,"@clickable":true,"@enabled":true,"@focusable":true,"@focused":false,"@scrollable":false,"@long-clickable":false,"@selected":false,"@editable":false,"@bounds":"[0,749][836,881]","@screenBounds":"[0,0][1080,2280]","node":{"@index":0,"@text":"Starred","@resource-id":"com.google.android.gm:id\/hub_drawer_label_title","@class":"android.widget.TextView","@package":"com.google.android.gm","@checkable":false,"@checked":false,"@clickable":false,"@enabled":true,"@focusable":false,"@focused":false,"@scrollable":false,"@long-clickable":false,"@selected":false,"@editable":false,"@bounds":"[198,784][814,845]","@screenBounds":"[0,0][1080,2280]"}}},{"@index":6,"@resource-id":"com.google.android.gm:id\/label_view","@class":"android.widget.LinearLayout","@package":"com.google.android.gm","@checkable":false,"@checked":false,"@clickable":false,"@enabled":true,"@focusable":false,"@focused":false,"@scrollable":false,"@long-clickable":false,"@selected":false,"@editable":false,"@bounds":"[0,881][836,1013]","@screenBounds":"[0,0][1080,2280]","node":{"@index":0,"@resource-id":"com.google.android.gm:id\/hub_drawer_label_container","@class":"android.widget.LinearLayout","@package":"com.google.android.gm","@checkable":false,"@checked":false,"@clickable":true,"@enabled":true,"@focusable":true,"@focused":false,"@scrollable":false,"@long-clickable":false,"@selected":false,"@editable":false,"@bounds":"[0,881][836,1013]","@screenBounds":"[0,0][1080,2280]","node":{"@index":0,"@text":"Snoozed","@resource-id":"com.google.android.gm:id\/hub_drawer_label_title","@class":"android.widget.TextView","@package":"com.google.android.gm","@checkable":false,"@checked":false,"@clickable":false,"@enabled":true,"@focusable":false,"@focused":false,"@scrollable":false,"@long-clickable":false,"@selected":false,"@editable":false,"@bounds":"[198,916][814,977]","@screenBounds":"[0,0][1080,2280]"}}},{"@index":7,"@resource-id":"com.google.android.gm:id\/label_view","@class":"android.widget.LinearLayout","@package":"com.google.android.gm","@checkable":false,"@checked":false,"@clickable":false,"@enabled":true,"@focusable":false,"@focused":false,"@scrollable":false,"@long-clickable":false,"@selected":false,"@editable":false,"@bounds":"[0,1013][836,1145]","@screenBounds":"[0,0][1080,2280]","node":{"@index":0,"@resource-id":"com.google.android.gm:id\/hub_drawer_label_container","@class":"android.widget.LinearLayout","@package":"com.google.android.gm","@checkable":false,"@checked":false,"@clickable":true,"@enabled":true,"@focusable":true,"@focused":false,"@scrollable":false,"@long-clickable":false,"@selected":false,"@editable":false,"@bounds":"[0,1013][836,1145]","@screenBounds":"[0,0][1080,2280]","node":[{"@index":0,"@text":"Important","@resource-id":"com.google.android.gm:id\/hub_drawer_label_title","@class":"android.widget.TextView","@package":"com.google.android.gm","@checkable":false,"@checked":false,"@clickable":false,"@enabled":true,"@focusable":false,"@focused":false,"@scrollable":false,"@long-clickable":false,"@selected":false,"@editable":false,"@bounds":"[198,1048][594,1109]","@screenBounds":"[0,0][1080,2280]"},{"@index":1,"@text":"3","@resource-id":"com.google.android.gm:id\/count","@class":"android.widget.TextView","@package":"com.google.android.gm","@checkable":false,"@checked":false,"@clickable":false,"@enabled":true,"@focusable":false,"@focused":false,"@scrollable":false,"@long-clickable":false,"@selected":false,"@editable":false,"@bounds":"[660,1053][770,1105]","@screenBounds":"[0,0][1080,2280]"}]}},{"@index":8,"@resource-id":"com.google.android.gm:id\/label_view","@class":"android.widget.LinearLayout","@package":"com.google.android.gm","@checkable":false,"@checked":false,"@clickable":false,"@enabled":true,"@focusable":false,"@focused":false,"@scrollable":false,"@long-clickable":false,"@selected":false,"@editable":false,"@bounds":"[0,1145][836,1277]","@screenBounds":"[0,0][1080,2280]","node":{"@index":0,"@resource-id":"com.google.android.gm:id\/hub_drawer_label_container","@class":"android.widget.LinearLayout","@package":"com.google.android.gm","@checkable":false,"@checked":false,"@clickable":true,"@enabled":true,"@focusable":true,"@focused":false,"@scrollable":false,"@long-clickable":false,"@selected":false,"@editable":false,"@bounds":"[0,1145][836,1277]","@screenBounds":"[0,0][1080,2280]","node":{"@index":0,"@text":"Sent","@resource-id":"com.google.android.gm:id\/hub_drawer_label_title","@class":"android.widget.TextView","@package":"com.google.android.gm","@checkable":false,"@checked":false,"@clickable":false,"@enabled":true,"@focusable":false,"@focused":false,"@scrollable":false,"@long-clickable":false,"@selected":false,"@editable":false,"@bounds":"[198,1180][814,1241]","@screenBounds":"[0,0][1080,2280]"}}},{"@index":9,"@resource-id":"com.google.android.gm:id\/label_view","@class":"android.widget.LinearLayout","@package":"com.google.android.gm","@checkable":false,"@checked":false,"@clickable":false,"@enabled":true,"@focusable":false,"@focused":false,"@scrollable":false,"@long-clickable":false,"@selected":false,"@editable":false,"@bounds":"[0,1277][836,1409]","@screenBounds":"[0,0][1080,2280]","node":{"@index":0,"@resource-id":"com.google.android.gm:id\/hub_drawer_label_container","@class":"android.widget.LinearLayout","@package":"com.google.android.gm","@checkable":false,"@checked":false,"@clickable":true,"@enabled":true,"@focusable":true,"@focused":false,"@scrollable":false,"@long-clickable":false,"@selected":false,"@editable":false,"@bounds":"[0,1277][836,1409]","@screenBounds":"[0,0][1080,2280]","node":{"@index":0,"@text":"Scheduled","@resource-id":"com.google.android.gm:id\/hub_drawer_label_title","@class":"android.widget.TextView","@package":"com.google.android.gm","@checkable":false,"@checked":false,"@clickable":false,"@enabled":true,"@focusable":false,"@focused":false,"@scrollable":false,"@long-clickable":false,"@selected":false,"@editable":false,"@bounds":"[198,1312][814,1373]","@screenBounds":"[0,0][1080,2280]"}}},{"@index":10,"@resource-id":"com.google.android.gm:id\/label_view","@class":"android.widget.LinearLayout","@package":"com.google.android.gm","@checkable":false,"@checked":false,"@clickable":false,"@enabled":true,"@focusable":false,"@focused":false,"@scrollable":false,"@long-clickable":false,"@selected":false,"@editable":false,"@bounds":"[0,1409][836,1541]","@screenBounds":"[0,0][1080,2280]","node":{"@index":0,"@resource-id":"com.google.android.gm:id\/hub_drawer_label_container","@class":"android.widget.LinearLayout","@package":"com.google.android.gm","@checkable":false,"@checked":false,"@clickable":true,"@enabled":true,"@focusable":true,"@focused":false,"@scrollable":false,"@long-clickable":false,"@selected":false,"@editable":false,"@bounds":"[0,1409][836,1541]","@screenBounds":"[0,0][1080,2280]","node":{"@index":0,"@text":"Outbox","@resource-id":"com.google.android.gm:id\/hub_drawer_label_title","@class":"android.widget.TextView","@package":"com.google.android.gm","@checkable":false,"@checked":false,"@clickable":false,"@enabled":true,"@focusable":false,"@focused":false,"@scrollable":false,"@long-clickable":false,"@selected":false,"@editable":false,"@bounds":"[198,1444][814,1505]","@screenBounds":"[0,0][1080,2280]"}}},{"@index":11,"@resource-id":"com.google.android.gm:id\/label_view","@class":"android.widget.LinearLayout","@package":"com.google.android.gm","@checkable":false,"@checked":false,"@clickable":false,"@enabled":true,"@focusable":false,"@focused":false,"@scrollable":false,"@long-clickable":false,"@selected":false,"@editable":false,"@bounds":"[0,1541][836,1673]","@screenBounds":"[0,0][1080,2280]","node":{"@index":0,"@resource-id":"com.google.android.gm:id\/hub_drawer_label_container","@class":"android.widget.LinearLayout","@package":"com.google.android.gm","@checkable":false,"@checked":false,"@clickable":true,"@enabled":true,"@focusable":true,"@focused":false,"@scrollable":false,"@long-clickable":false,"@selected":false,"@editable":false,"@bounds":"[0,1541][836,1673]","@screenBounds":"[0,0][1080,2280]","node":{"@index":0,"@text":"Drafts","@resource-id":"com.google.android.gm:id\/hub_drawer_label_title","@class":"android.widget.TextView","@package":"com.google.android.gm","@checkable":false,"@checked":false,"@clickable":false,"@enabled":true,"@focusable":false,"@focused":false,"@scrollable":false,"@long-clickable":false,"@selected":false,"@editable":false,"@bounds":"[198,1576][814,1637]","@screenBounds":"[0,0][1080,2280]"}}},{"@index":12,"@resource-id":"com.google.android.gm:id\/label_view","@class":"android.widget.LinearLayout","@package":"com.google.android.gm","@checkable":false,"@checked":false,"@clickable":false,"@enabled":true,"@focusable":false,"@focused":false,"@scrollable":false,"@long-clickable":false,"@selected":false,"@editable":false,"@bounds":"[0,1673][836,1805]","@screenBounds":"[0,0][1080,2280]","node":{"@index":0,"@resource-id":"com.google.android.gm:id\/hub_drawer_label_container","@class":"android.widget.LinearLayout","@package":"com.google.android.gm","@checkable":false,"@checked":false,"@clickable":true,"@enabled":true,"@focusable":true,"@focused":false,"@scrollable":false,"@long-clickable":false,"@selected":false,"@editable":false,"@bounds":"[0,1673][836,1805]","@screenBounds":"[0,0][1080,2280]","node":[{"@index":0,"@text":"All mail","@resource-id":"com.google.android.gm:id\/hub_drawer_label_title","@class":"android.widget.TextView","@package":"com.google.android.gm","@checkable":false,"@checked":false,"@clickable":false,"@enabled":true,"@focusable":false,"@focused":false,"@scrollable":false,"@long-clickable":false,"@selected":false,"@editable":false,"@bounds":"[198,1708][594,1769]","@screenBounds":"[0,0][1080,2280]"},{"@index":1,"@text":"58","@resource-id":"com.google.android.gm:id\/count","@class":"android.widget.TextView","@package":"com.google.android.gm","@checkable":false,"@checked":false,"@clickable":false,"@enabled":true,"@focusable":false,"@focused":false,"@scrollable":false,"@long-clickable":false,"@selected":false,"@editable":false,"@bounds":"[660,1713][770,1765]","@screenBounds":"[0,0][1080,2280]"}]}},{"@index":13,"@resource-id":"com.google.android.gm:id\/label_view","@class":"android.widget.LinearLayout","@package":"com.google.android.gm","@checkable":false,"@checked":false,"@clickable":false,"@enabled":true,"@focusable":false,"@focused":false,"@scrollable":false,"@long-clickable":false,"@selected":false,"@editable":false,"@bounds":"[0,1805][836,1937]","@screenBounds":"[0,0][1080,2280]","node":{"@index":0,"@resource-id":"com.google.android.gm:id\/hub_drawer_label_container","@class":"android.widget.LinearLayout","@package":"com.google.android.gm","@checkable":false,"@checked":false,"@clickable":true,"@enabled":true,"@focusable":true,"@focused":false,"@scrollable":false,"@long-clickable":false,"@selected":false,"@editable":false,"@bounds":"[0,1805][836,1937]","@screenBounds":"[0,0][1080,2280]","node":[{"@index":0,"@text":"Spam","@resource-id":"com.google.android.gm:id\/hub_drawer_label_title","@class":"android.widget.TextView","@package":"com.google.android.gm","@checkable":false,"@checked":false,"@clickable":false,"@enabled":true,"@focusable":false,"@focused":false,"@scrollable":false,"@long-clickable":false,"@selected":false,"@editable":false,"@bounds":"[198,1840][594,1901]","@screenBounds":"[0,0][1080,2280]"},{"@index":1,"@text":"4","@resource-id":"com.google.android.gm:id\/count","@class":"android.widget.TextView","@package":"com.google.android.gm","@checkable":false,"@checked":false,"@clickable":false,"@enabled":true,"@focusable":false,"@focused":false,"@scrollable":false,"@long-clickable":false,"@selected":false,"@editable":false,"@bounds":"[660,1845][770,1897]","@screenBounds":"[0,0][1080,2280]"}]}},{"@index":14,"@resource-id":"com.google.android.gm:id\/label_view","@class":"android.widget.LinearLayout","@package":"com.google.android.gm","@checkable":false,"@checked":false,"@clickable":false,"@enabled":true,"@focusable":false,"@focused":false,"@scrollable":false,"@long-clickable":false,"@selected":false,"@editable":false,"@bounds":"[0,1937][836,2069]","@screenBounds":"[0,0][1080,2280]","node":{"@index":0,"@resource-id":"com.google.android.gm:id\/hub_drawer_label_container","@class":"android.widget.LinearLayout","@package":"com.google.android.gm","@checkable":false,"@checked":false,"@clickable":true,"@enabled":true,"@focusable":true,"@focused":false,"@scrollable":false,"@long-clickable":false,"@selected":false,"@editable":false,"@bounds":"[0,1937][836,2069]","@screenBounds":"[0,0][1080,2280]","node":[{"@index":0,"@text":"Trash","@resource-id":"com.google.android.gm:id\/hub_drawer_label_title","@class":"android.widget.TextView","@package":"com.google.android.gm","@checkable":false,"@checked":false,"@clickable":false,"@enabled":true,"@focusable":false,"@focused":false,"@scrollable":false,"@long-clickable":false,"@selected":false,"@editable":false,"@bounds":"[198,1972][594,2033]","@screenBounds":"[0,0][1080,2280]"},{"@index":1,"@text":"3","@resource-id":"com.google.android.gm:id\/count","@class":"android.widget.TextView","@package":"com.google.android.gm","@checkable":false,"@checked":false,"@clickable":false,"@enabled":true,"@focusable":false,"@focused":false,"@scrollable":false,"@long-clickable":false,"@selected":false,"@editable":false,"@bounds":"[660,1977][770,2029]","@screenBounds":"[0,0][1080,2280]"}]}},{"@index":15,"@resource-id":"com.google.android.gm:id\/label_view","@class":"android.widget.LinearLayout","@package":"com.google.android.gm","@checkable":false,"@checked":false,"@clickable":false,"@enabled":true,"@focusable":false,"@focused":false,"@scrollable":false,"@long-clickable":false,"@selected":false,"@editable":false,"@bounds":"[0,2069][836,2201]","@screenBounds":"[0,0][1080,2280]","node":{"@index":0,"@resource-id":"com.google.android.gm:id\/hub_drawer_label_container","@class":"android.widget.LinearLayout","@package":"com.google.android.gm","@checkable":false,"@checked":false,"@clickable":true,"@enabled":true,"@focusable":true,"@focused":false,"@scrollable":false,"@long-clickable":false,"@selected":false,"@editable":false,"@bounds":"[0,2069][836,2201]","@screenBounds":"[0,0][1080,2280]","node":{"@index":0,"@text":"Notes","@resource-id":"com.google.android.gm:id\/hub_drawer_label_title","@class":"android.widget.TextView","@package":"com.google.android.gm","@checkable":false,"@checked":false,"@clickable":false,"@enabled":true,"@focusable":false,"@focused":false,"@scrollable":false,"@long-clickable":false,"@selected":false,"@editable":false,"@bounds":"[198,2104][814,2165]","@screenBounds":"[0,0][1080,2280]"}}},{"@index":16,"@class":"android.widget.LinearLayout","@package":"com.google.android.gm","@checkable":false,"@checked":false,"@clickable":false,"@enabled":true,"@focusable":false,"@focused":false,"@scrollable":false,"@long-clickable":false,"@selected":false,"@editable":false,"@bounds":"[0,2201][836,2214]","@screenBounds":"[0,0][1080,2280]","node":{"@index":0,"@text":"Google apps","@resource-id":"com.google.android.gm:id\/drawer_category_title","@class":"android.widget.TextView","@package":"com.google.android.gm","@checkable":false,"@checked":false,"@clickable":false,"@enabled":true,"@focusable":false,"@focused":false,"@scrollable":false,"@long-clickable":false,"@selected":false,"@editable":false,"@bounds":"[0,2201][836,2214]","@screenBounds":"[0,0][1080,2280]"}}]}}}]}}}}}}